{
  "version": "6",
  "dialect": "sqlite",
  "id": "19edf275-c665-422b-a8ad-b90e3c6c3b7f",
  "prevId": "00000000-0000-0000-0000-000000000000",
  "tables": {
    "audit_log": {
      "name": "audit_log",
      "columns": {
        "id": {
          "name": "id",
          "type": "integer",
          "primaryKey": true,
          "notNull": true,
          "autoincrement": true
        },
        "flagged_item_id": {
          "name": "flagged_item_id",
          "type": "integer",
          "primaryKey": false,
          "notNull": true,
          "autoincrement": false
        },
        "scan_run_id": {
          "name": "scan_run_id",
          "type": "integer",
          "primaryKey": false,
          "notNull": true,
          "autoincrement": false
        },
        "torrent_name": {
          "name": "torrent_name",
          "type": "text",
          "primaryKey": false,
          "notNull": true,
          "autoincrement": false
        },
        "torrent_hash": {
          "name": "torrent_hash",
          "type": "text",
          "primaryKey": false,
          "notNull": true,
          "autoincrement": false
        },
        "category": {
          "name": "category",
          "type": "text",
          "primaryKey": false,
          "notNull": true,
          "autoincrement": false
        },
        "files_deleted": {
          "name": "files_deleted",
          "type": "text",
          "primaryKey": false,
          "notNull": true,
          "autoincrement": false
        },
        "triggered_by": {
          "name": "triggered_by",
          "type": "text",
          "primaryKey": false,
          "notNull": true,
          "autoincrement": false
        },
        "created_at": {
          "name": "created_at",
          "type": "text",
          "primaryKey": false,
          "notNull": true,
          "autoincrement": false
        }
      },
      "indexes": {},
      "foreignKeys": {
        "audit_log_flagged_item_id_flagged_items_id_fk": {
          "name": "audit_log_flagged_item_id_flagged_items_id_fk",
          "tableFrom": "audit_log",
          "tableTo": "flagged_items",
          "columnsFrom": ["flagged_item_id"],
          "columnsTo": ["id"],
          "onDelete": "cascade",
          "onUpdate": "no action"
        },
        "audit_log_scan_run_id_scan_runs_id_fk": {
          "name": "audit_log_scan_run_id_scan_runs_id_fk",
          "tableFrom": "audit_log",
          "tableTo": "scan_runs",
          "columnsFrom": ["scan_run_id"],
          "columnsTo": ["id"],
          "onDelete": "cascade",
          "onUpdate": "no action"
        }
      },
      "compositePrimaryKeys": {},
      "uniqueConstraints": {},
      "checkConstraints": {}
    },
    "config": {
      "name": "config",
      "columns": {
        "key": {
          "name": "key",
          "type": "text",
          "primaryKey": true,
          "notNull": true,
          "autoincrement": false
        },
        "value": {
          "name": "value",
          "type": "text",
          "primaryKey": false,
          "notNull": true,
          "autoincrement": false
        }
      },
      "indexes": {},
      "foreignKeys": {},
      "compositePrimaryKeys": {},
      "uniqueConstraints": {},
      "checkConstraints": {}
    },
    "flagged_items": {
      "name": "flagged_items",
      "columns": {
        "id": {
          "name": "id",
          "type": "integer",
          "primaryKey": true,
          "notNull": true,
          "autoincrement": true
        },
        "scan_run_id": {
          "name": "scan_run_id",
          "type": "integer",
          "primaryKey": false,
          "notNull": true,
          "autoincrement": false
        },
        "qbittorrent_instance_id": {
          "name": "qbittorrent_instance_id",
          "type": "integer",
          "primaryKey": false,
          "notNull": true,
          "autoincrement": false
        },
        "arr_instance_id": {
          "name": "arr_instance_id",
          "type": "integer",
          "primaryKey": false,
          "notNull": false,
          "autoincrement": false
        },
        "category": {
          "name": "category",
          "type": "text",
          "primaryKey": false,
          "notNull": true,
          "autoincrement": false
        },
        "reason": {
          "name": "reason",
          "type": "text",
          "primaryKey": false,
          "notNull": true,
          "autoincrement": false
        },
        "torrent_hash": {
          "name": "torrent_hash",
          "type": "text",
          "primaryKey": false,
          "notNull": false,
          "autoincrement": false
        },
        "torrent_name": {
          "name": "torrent_name",
          "type": "text",
          "primaryKey": false,
          "notNull": false,
          "autoincrement": false
        },
        "torrent_size": {
          "name": "torrent_size",
          "type": "integer",
          "primaryKey": false,
          "notNull": false,
          "autoincrement": false
        },
        "torrent_tags": {
          "name": "torrent_tags",
          "type": "text",
          "primaryKey": false,
          "notNull": false,
          "autoincrement": false
        },
        "files_to_delete": {
          "name": "files_to_delete",
          "type": "text",
          "primaryKey": false,
          "notNull": false,
          "autoincrement": false
        },
        "status": {
          "name": "status",
          "type": "text",
          "primaryKey": false,
          "notNull": true,
          "autoincrement": false,
          "default": "'pending'"
        },
        "dismissed_at": {
          "name": "dismissed_at",
          "type": "text",
          "primaryKey": false,
          "notNull": false,
          "autoincrement": false
        },
        "approved_at": {
          "name": "approved_at",
          "type": "text",
          "primaryKey": false,
          "notNull": false,
          "autoincrement": false
        },
        "created_at": {
          "name": "created_at",
          "type": "text",
          "primaryKey": false,
          "notNull": true,
          "autoincrement": false
        }
      },
      "indexes": {
        "flagged_items_status_idx": {
          "name": "flagged_items_status_idx",
          "columns": ["status"],
          "isUnique": false
        },
        "flagged_items_scan_run_id_idx": {
          "name": "flagged_items_scan_run_id_idx",
          "columns": ["scan_run_id"],
          "isUnique": false
        }
      },
      "foreignKeys": {
        "flagged_items_scan_run_id_scan_runs_id_fk": {
          "name": "flagged_items_scan_run_id_scan_runs_id_fk",
          "tableFrom": "flagged_items",
          "tableTo": "scan_runs",
          "columnsFrom": ["scan_run_id"],
          "columnsTo": ["id"],
          "onDelete": "cascade",
          "onUpdate": "no action"
        },
        "flagged_items_qbittorrent_instance_id_instances_id_fk": {
          "name": "flagged_items_qbittorrent_instance_id_instances_id_fk",
          "tableFrom": "flagged_items",
          "tableTo": "instances",
          "columnsFrom": ["qbittorrent_instance_id"],
          "columnsTo": ["id"],
          "onDelete": "cascade",
          "onUpdate": "no action"
        },
        "flagged_items_arr_instance_id_instances_id_fk": {
          "name": "flagged_items_arr_instance_id_instances_id_fk",
          "tableFrom": "flagged_items",
          "tableTo": "instances",
          "columnsFrom": ["arr_instance_id"],
          "columnsTo": ["id"],
          "onDelete": "set null",
          "onUpdate": "no action"
        }
      },
      "compositePrimaryKeys": {},
      "uniqueConstraints": {},
      "checkConstraints": {}
    },
    "instances": {
      "name": "instances",
      "columns": {
        "id": {
          "name": "id",
          "type": "integer",
          "primaryKey": true,
          "notNull": true,
          "autoincrement": true
        },
        "type": {
          "name": "type",
          "type": "text",
          "primaryKey": false,
          "notNull": true,
          "autoincrement": false
        },
        "label": {
          "name": "label",
          "type": "text",
          "primaryKey": false,
          "notNull": true,
          "autoincrement": false
        },
        "url": {
          "name": "url",
          "type": "text",
          "primaryKey": false,
          "notNull": true,
          "autoincrement": false
        },
        "username": {
          "name": "username",
          "type": "text",
          "primaryKey": false,
          "notNull": false,
          "autoincrement": false
        },
        "password": {
          "name": "password",
          "type": "text",
          "primaryKey": false,
          "notNull": false,
          "autoincrement": false
        },
        "api_key": {
          "name": "api_key",
          "type": "text",
          "primaryKey": false,
          "notNull": false,
          "autoincrement": false
        },
        "download_dir": {
          "name": "download_dir",
          "type": "text",
          "primaryKey": false,
          "notNull": false,
          "autoincrement": false
        },
        "radarr_tag": {
          "name": "radarr_tag",
          "type": "text",
          "primaryKey": false,
          "notNull": false,
          "autoincrement": false,
          "default": "'radarr'"
        },
        "sonarr_tag": {
          "name": "sonarr_tag",
          "type": "text",
          "primaryKey": false,
          "notNull": false,
          "autoincrement": false,
          "default": "'sonarr'"
        },
        "linked_qbittorrent_id": {
          "name": "linked_qbittorrent_id",
          "type": "integer",
          "primaryKey": false,
          "notNull": false,
          "autoincrement": false
        },
        "created_at": {
          "name": "created_at",
          "type": "text",
          "primaryKey": false,
          "notNull": true,
          "autoincrement": false
        }
      },
      "indexes": {},
      "foreignKeys": {},
      "compositePrimaryKeys": {},
      "uniqueConstraints": {},
      "checkConstraints": {}
    },
    "library_snapshots": {
      "name": "library_snapshots",
      "columns": {
        "id": {
          "name": "id",
          "type": "integer",
          "primaryKey": true,
          "notNull": true,
          "autoincrement": true
        },
        "scan_run_id": {
          "name": "scan_run_id",
          "type": "integer",
          "primaryKey": false,
          "notNull": true,
          "autoincrement": false
        },
        "instance_id": {
          "name": "instance_id",
          "type": "integer",
          "primaryKey": false,
          "notNull": true,
          "autoincrement": false
        },
        "data": {
          "name": "data",
          "type": "text",
          "primaryKey": false,
          "notNull": true,
          "autoincrement": false
        },
        "created_at": {
          "name": "created_at",
          "type": "text",
          "primaryKey": false,
          "notNull": true,
          "autoincrement": false
        }
      },
      "indexes": {},
      "foreignKeys": {
        "library_snapshots_scan_run_id_scan_runs_id_fk": {
          "name": "library_snapshots_scan_run_id_scan_runs_id_fk",
          "tableFrom": "library_snapshots",
          "tableTo": "scan_runs",
          "columnsFrom": ["scan_run_id"],
          "columnsTo": ["id"],
          "onDelete": "cascade",
          "onUpdate": "no action"
        },
        "library_snapshots_instance_id_instances_id_fk": {
          "name": "library_snapshots_instance_id_instances_id_fk",
          "tableFrom": "library_snapshots",
          "tableTo": "instances",
          "columnsFrom": ["instance_id"],
          "columnsTo": ["id"],
          "onDelete": "cascade",
          "onUpdate": "no action"
        }
      },
      "compositePrimaryKeys": {},
      "uniqueConstraints": {},
      "checkConstraints": {}
    },
    "scan_runs": {
      "name": "scan_runs",
      "columns": {
        "id": {
          "name": "id",
          "type": "integer",
          "primaryKey": true,
          "notNull": true,
          "autoincrement": true
        },
        "started_at": {
          "name": "started_at",
          "type": "text",
          "primaryKey": false,
          "notNull": true,
          "autoincrement": false
        },
        "completed_at": {
          "name": "completed_at",
          "type": "text",
          "primaryKey": false,
          "notNull": false,
          "autoincrement": false
        },
        "status": {
          "name": "status",
          "type": "text",
          "primaryKey": false,
          "notNull": true,
          "autoincrement": false,
          "default": "'running'"
        },
        "summary": {
          "name": "summary",
          "type": "text",
          "primaryKey": false,
          "notNull": false,
          "autoincrement": false
        },
        "triggered_by": {
          "name": "triggered_by",
          "type": "text",
          "primaryKey": false,
          "notNull": true,
          "autoincrement": false,
          "default": "'manual'"
        }
      },
      "indexes": {},
      "foreignKeys": {},
      "compositePrimaryKeys": {},
      "uniqueConstraints": {},
      "checkConstraints": {}
    }
  },
  "views": {},
  "enums": {},
  "_meta": {
    "schemas": {},
    "tables": {},
    "columns": {}
  },
  "internal": {
    "indexes": {}
  }
}
